test/verilog/counter.v
// ====================================================================
// ======= This Verilog code was generated automatically by wiRedPanda =======
// ====================================================================
//
// Module: counter
// Generated: Fri Sep 26 15:18:21 2025
// Target FPGA: Generic-Small
// Resource Usage: 8/1000 LUTs, 38/1000 FFs, 4/50 IOs
//
// wiRedPanda - Digital Logic Circuit Simulator
// https://github.com/gibis-unifesp/wiredpanda
// ====================================================================

module counter (
    // ========= Input Ports =========
    input wire input_clock1_1,

    // ========= Output Ports =========
    output wire output_led1_0_2,
    output wire output_led2_0_3,
    output wire output_led3_0_4
);

    // ========= Internal Signals =========
    reg jk_flip_flop_5_0_q = 1'b0;
    reg jk_flip_flop_5_1_q = 1'b0;
    reg jk_flip_flop_6_0_q = 1'b0;
    reg jk_flip_flop_6_1_q = 1'b0;
    reg jk_flip_flop_7_0_q = 1'b0;
    reg jk_flip_flop_7_1_q = 1'b0;

    // ========= Logic Assignments =========
    // JK FlipFlop: JK-Flip-Flop
    always @(posedge jk_flip_flop_6_0_q) begin
        begin
            case ({1'b1, 1'b1})
                2'b00: begin /* hold */ end
                2'b01: begin jk_flip_flop_7_0_q <= 1'b0; jk_flip_flop_7_1_q <= 1'b1; end
                2'b10: begin jk_flip_flop_7_0_q <= 1'b1; jk_flip_flop_7_1_q <= 1'b0; end
                2'b11: begin jk_flip_flop_7_0_q <= jk_flip_flop_7_1_q; jk_flip_flop_7_1_q <= jk_flip_flop_7_0_q; end // toggle
            endcase
        end
    end

    // JK FlipFlop: JK-Flip-Flop
    always @(posedge jk_flip_flop_5_0_q) begin
        begin
            case ({1'b1, 1'b1})
                2'b00: begin /* hold */ end
                2'b01: begin jk_flip_flop_6_0_q <= 1'b0; jk_flip_flop_6_1_q <= 1'b1; end
                2'b10: begin jk_flip_flop_6_0_q <= 1'b1; jk_flip_flop_6_1_q <= 1'b0; end
                2'b11: begin jk_flip_flop_6_0_q <= jk_flip_flop_6_1_q; jk_flip_flop_6_1_q <= jk_flip_flop_6_0_q; end // toggle
            endcase
        end
    end

    // JK FlipFlop: JK-Flip-Flop
    always @(posedge input_clock1_1) begin
        begin
            case ({1'b1, 1'b1})
                2'b00: begin /* hold */ end
                2'b01: begin jk_flip_flop_5_0_q <= 1'b0; jk_flip_flop_5_1_q <= 1'b1; end
                2'b10: begin jk_flip_flop_5_0_q <= 1'b1; jk_flip_flop_5_1_q <= 1'b0; end
                2'b11: begin jk_flip_flop_5_0_q <= jk_flip_flop_5_1_q; jk_flip_flop_5_1_q <= jk_flip_flop_5_0_q; end // toggle
            endcase
        end
    end


    // ========= Output Assignments =========
    assign output_led1_0_2 = jk_flip_flop_7_1_q; // LED
    assign output_led2_0_3 = jk_flip_flop_6_1_q; // LED
    assign output_led3_0_4 = jk_flip_flop_5_1_q; // LED

endmodule // counter

// ====================================================================
// Module counter generation completed successfully
// Elements processed: 7
// Inputs: 1, Outputs: 3
// ====================================================================

test/verilog/counter_tb.v
`timescale 1ns / 1ps

module counter_tb;

    // Testbench signals
    reg input_clock1_1;
    wire output_led1_0_2;
    wire output_led2_0_3;
    wire output_led3_0_4;

    // Test control
    integer test_count = 0;
    integer cycle_count = 0;
    reg [2:0] expected_count = 0;
    reg [2:0] actual_count;

    // Instantiate the Device Under Test (DUT)
    counter dut (
        .input_clock1_1(input_clock1_1),
        .output_led1_0_2(output_led1_0_2),
        .output_led2_0_3(output_led2_0_3),
        .output_led3_0_4(output_led3_0_4)
    );

    // Clock generation (10MHz = 100ns period)
    always begin
        #50 input_clock1_1 = ~input_clock1_1;
    end

    // Pack outputs into a 3-bit counter value
    always @(*) begin
        actual_count = {output_led1_0_2, output_led2_0_3, output_led3_0_4};
    end

    // Monitor and verify counter behavior
    always @(posedge input_clock1_1) begin
        cycle_count = cycle_count + 1;
        #10; // Wait for propagation delay

        $display("Cycle %0d: Count = %b%b%b (%0d)",
                 cycle_count, output_led1_0_2, output_led2_0_3, output_led3_0_4, actual_count);

        // After first few cycles, start checking expected behavior
        if (cycle_count > 3) begin
            test_count = test_count + 1;
            // For a 3-bit counter, we expect: 000 -> 001 -> 010 -> 011 -> 100 -> 101 -> 110 -> 111 -> 000...
            // Note: This assumes the counter starts at 0 and increments
        end
    end

    // Main test sequence
    initial begin
        $display("=== COUNTER TESTBENCH ===");
        $display("Testing 3-bit JK flip-flop counter");

        // Initialize signals
        input_clock1_1 = 0;

        // Wait for reset/initialization
        #100;

        // Run for several clock cycles to observe counter behavior
        #2000; // 20 clock cycles

        // Summary
        $display("\n=== TEST SUMMARY ===");
        $display("Total clock cycles: %0d", cycle_count);
        $display("Counter appears to be functioning");
        $display("Final count: %b%b%b (%0d)", output_led1_0_2, output_led2_0_3, output_led3_0_4, actual_count);

        $finish;
    end

    // Optional: Generate VCD file for waveform viewing
    initial begin
        $dumpfile("counter_tb.vcd");
        $dumpvars(0, counter_tb);
    end

endmodule

test/verilog/counter_tb.vcd
$date
	Fri Sep 26 21:01:38 2025
$end
$version
	Icarus Verilog
$end
$timescale
	1ps
$end
$scope module counter_tb $end
$var wire 1 ! output_led3_0_4 $end
$var wire 1 " output_led2_0_3 $end
$var wire 1 # output_led1_0_2 $end
$var reg 3 $ actual_count [2:0] $end
$var reg 3 % expected_count [2:0] $end
$var reg 1 & input_clock1_1 $end
$var integer 32 ' cycle_count [31:0] $end
$var integer 32 ( test_count [31:0] $end
$scope module dut $end
$var wire 1 & input_clock1_1 $end
$var wire 1 # output_led1_0_2 $end
$var wire 1 " output_led2_0_3 $end
$var wire 1 ! output_led3_0_4 $end
$var reg 1 ) jk_flip_flop_5_0_q $end
$var reg 1 * jk_flip_flop_5_1_q $end
$var reg 1 + jk_flip_flop_6_0_q $end
$var reg 1 , jk_flip_flop_6_1_q $end
$var reg 1 - jk_flip_flop_7_0_q $end
$var reg 1 . jk_flip_flop_7_1_q $end
$upscope $end
$upscope $end
$enddefinitions $end
#0
$dumpvars
0.
0-
0,
0+
0*
0)
b0 (
b0 '
0&
b0 %
bx $
0#
0"
0!
$end
#50000
b1 '
1&
#100000
0&
#150000
b10 '
1&
#200000
0&
#250000
b11 '
1&
#300000
0&
#350000
b100 '
1&
#360000
b1 (
#400000
0&
#450000
b101 '
1&
#460000
b10 (
#500000
0&
#550000
b110 '
1&
#560000
b11 (
#600000
0&
#650000
b111 '
1&
#660000
b100 (
#700000
0&
#750000
b1000 '
1&
#760000
b101 (
#800000
0&
#850000
b1001 '
1&
#860000
b110 (
#900000
0&
#950000
b1010 '
1&
#960000
b111 (
#1000000
0&
#1050000
b1011 '
1&
#1060000
b1000 (
#1100000
0&
#1150000
b1100 '
1&
#1160000
b1001 (
#1200000
0&
#1250000
b1101 '
1&
#1260000
b1010 (
#1300000
0&
#1350000
b1110 '
1&
#1360000
b1011 (
#1400000
0&
#1450000
b1111 '
1&
#1460000
b1100 (
#1500000
0&
#1550000
b10000 '
1&
#1560000
b1101 (
#1600000
0&
#1650000
b10001 '
1&
#1660000
b1110 (
#1700000
0&
#1750000
b10010 '
1&
#1760000
b1111 (
#1800000
0&
#1850000
b10011 '
1&
#1860000
b10000 (
#1900000
0&
#1950000
b10100 '
1&
#1960000
b10001 (
#2000000
0&
#2050000
b10101 '
1&
#2060000
b10010 (
