test/verilog/decoder.v
// ====================================================================
// ======= This Verilog code was generated automatically by wiRedPanda =======
// ====================================================================
//
// Module: decoder
// Generated: Fri Sep 26 19:56:44 2025
// Target FPGA: Generic-Small
// Resource Usage: 66/1000 LUTs, 0/1000 FFs, 12/50 IOs
//
// wiRedPanda - Digital Logic Circuit Simulator
// https://github.com/gibis-unifesp/wiredpanda
// ====================================================================

module decoder (
    // ========= Input Ports =========
    input wire input_input_switch1_1,
    input wire input_input_switch2_2,
    input wire input_input_switch3_3,

    // ========= Output Ports =========
    output wire output_led1_0_4,
    output wire output_led2_0_5,
    output wire output_led3_0_6,
    output wire output_led4_0_7,
    output wire output_led5_0_8,
    output wire output_led6_0_9,
    output wire output_led7_0_10,
    output wire output_led8_0_11
);

    // ========= Internal Signals =========
    wire node_12;
    wire node_13;
    wire node_14;
    wire not_15;
    wire not_16;
    wire not_17;
    wire node_18;
    wire node_19;
    wire node_20;
    wire node_21;
    wire node_22;
    wire node_23;
    wire node_24;
    wire node_25;
    wire node_26;
    wire node_27;
    wire node_28;
    wire node_29;
    wire node_30;
    wire node_31;
    wire node_32;
    wire node_33;
    wire node_34;
    wire node_35;
    wire node_36;
    wire node_37;
    wire node_38;
    wire node_39;
    wire node_40;
    wire node_41;
    wire and_42;
    wire and_43;
    wire and_44;
    wire and_45;
    wire and_46;
    wire and_47;
    wire and_48;
    wire and_49;
    wire node_50;
    wire node_51;
    wire node_52;
    wire node_53;
    wire node_54;
    wire node_55;

    // ========= Logic Assignments =========
    assign and_49 = (node_41 & node_40 & node_39); // And
    assign and_48 = (node_35 & node_34 & node_38); // And
    assign and_47 = (node_29 & node_37 & node_33); // And
    assign and_46 = (node_23 & node_31 & node_32); // And
    assign and_45 = (node_36 & node_28 & node_27); // And
    assign and_44 = (node_30 & node_22 & node_26); // And
    assign and_43 = (node_25 & node_24 & node_21); // And
    assign and_42 = (node_20 & node_19 & node_18); // And
    assign node_41 = node_35; // Node
    assign node_40 = node_34; // Node
    assign node_39 = node_33; // Node
    assign node_38 = node_32; // Node
    assign node_37 = node_31; // Node
    assign node_36 = node_30; // Node
    assign node_35 = node_29; // Node
    assign node_34 = node_28; // Node
    assign node_33 = node_27; // Node
    assign node_32 = node_26; // Node
    assign node_31 = node_24; // Node
    assign node_30 = node_25; // Node
    assign node_29 = node_23; // Node
    assign node_28 = node_22; // Node
    assign node_27 = node_21; // Node
    assign node_26 = node_20; // Node
    assign node_25 = node_18; // Node
    assign node_24 = node_19; // Node
    assign node_23 = node_12; // Node
    assign node_22 = node_13; // Node
    assign node_21 = node_14; // Node
    assign node_20 = not_17; // Node
    assign node_19 = not_16; // Node
    assign node_18 = not_15; // Node
    assign not_17 = ~node_14; // Not
    assign not_16 = ~node_13; // Not
    assign not_15 = ~node_12; // Not
    assign node_14 = input_input_switch2_2; // Node
    assign node_13 = input_input_switch1_1; // Node
    assign node_12 = input_input_switch3_3; // Node

    // ========= Output Assignments =========
    assign output_led1_0_4 = and_49; // LED
    assign output_led2_0_5 = and_48; // LED
    assign output_led3_0_6 = and_47; // LED
    assign output_led4_0_7 = and_46; // LED
    assign output_led5_0_8 = and_45; // LED
    assign output_led6_0_9 = and_44; // LED
    assign output_led7_0_10 = and_43; // LED
    assign output_led8_0_11 = and_42; // LED

endmodule // decoder

// ====================================================================
// Module decoder generation completed successfully
// Elements processed: 55
// Inputs: 3, Outputs: 8
// ====================================================================

test/verilog/decoder_tb.v
`timescale 1ns / 1ps

module decoder_tb;

    // Testbench signals
    reg input_input_switch1_1;
    reg input_input_switch2_2;
    reg input_input_switch3_3;
    wire output_led1_0_4;
    wire output_led2_0_5;
    wire output_led3_0_6;
    wire output_led4_0_7;
    wire output_led5_0_8;
    wire output_led6_0_9;
    wire output_led7_0_10;
    wire output_led8_0_11;

    // Test control
    integer test_count = 0;
    integer pass_count = 0;
    reg [2:0] input_value;
    reg [7:0] output_value;
    reg [7:0] expected_output;

    // Instantiate the Device Under Test (DUT)
    decoder dut (
        .input_input_switch1_1(input_input_switch1_1),
        .input_input_switch2_2(input_input_switch2_2),
        .input_input_switch3_3(input_input_switch3_3),
        .output_led1_0_4(output_led1_0_4),
        .output_led2_0_5(output_led2_0_5),
        .output_led3_0_6(output_led3_0_6),
        .output_led4_0_7(output_led4_0_7),
        .output_led5_0_8(output_led5_0_8),
        .output_led6_0_9(output_led6_0_9),
        .output_led7_0_10(output_led7_0_10),
        .output_led8_0_11(output_led8_0_11)
    );

    // Pack outputs into a single vector for easier checking
    always @(*) begin
        output_value = {output_led8_0_11, output_led7_0_10, output_led6_0_9, output_led5_0_8,
                       output_led4_0_7, output_led3_0_6, output_led2_0_5, output_led1_0_4};
    end

    // Test procedure for 3-to-8 decoder
    task test_decoder;
        input [2:0] inputs;
        begin
            test_count = test_count + 1;

            // Apply inputs
            {input_input_switch3_3, input_input_switch2_2, input_input_switch1_1} = inputs;
            input_value = inputs;

            // Calculate expected output (one-hot encoding)
            expected_output = 8'b00000001 << inputs;

            // Wait for combinational delay
            #10;

            // Check outputs
            if (output_value === expected_output) begin
                $display("PASS: Test %0d - Input: %3b (%0d), Output: %8b (expected: %8b)",
                         test_count, input_value, input_value, output_value, expected_output);
                pass_count = pass_count + 1;
            end else begin
                $display("FAIL: Test %0d - Input: %3b (%0d)", test_count, input_value, input_value);
                $display("      Expected: %8b", expected_output);
                $display("      Got:      %8b", output_value);
            end
        end
    endtask

    // Main test sequence
    initial begin
        $display("=== 3-TO-8 DECODER TESTBENCH ===");
        $display("Testing all 8 possible input combinations");

        // Initialize inputs
        input_input_switch1_1 = 0;
        input_input_switch2_2 = 0;
        input_input_switch3_3 = 0;

        // Wait for initialization
        #50;

        // Test all 8 input combinations (3-bit inputs: 000 to 111)
        test_decoder(3'b000); // Should activate output_led1_0_4
        test_decoder(3'b001); // Should activate output_led2_0_5
        test_decoder(3'b010); // Should activate output_led3_0_6
        test_decoder(3'b011); // Should activate output_led4_0_7
        test_decoder(3'b100); // Should activate output_led5_0_8
        test_decoder(3'b101); // Should activate output_led6_0_9
        test_decoder(3'b110); // Should activate output_led7_0_10
        test_decoder(3'b111); // Should activate output_led8_0_11

        // Summary
        $display("\n=== TEST SUMMARY ===");
        $display("Total tests: %0d", test_count);
        $display("Passed: %0d", pass_count);
        $display("Failed: %0d", test_count - pass_count);

        if (pass_count == test_count) begin
            $display("*** ALL TESTS PASSED ***");
        end else begin
            $display("*** SOME TESTS FAILED ***");
        end

        $finish;
    end

    // Optional: Generate VCD file for waveform viewing
    initial begin
        $dumpfile("decoder_tb.vcd");
        $dumpvars(0, decoder_tb);
    end

endmodule

test/verilog/decoder_tb.vcd
$date
	Fri Sep 26 21:01:38 2025
$end
$version
	Icarus Verilog
$end
$timescale
	1ps
$end
$scope module decoder_tb $end
$var wire 1 ! output_led8_0_11 $end
$var wire 1 " output_led7_0_10 $end
$var wire 1 # output_led6_0_9 $end
$var wire 1 $ output_led5_0_8 $end
$var wire 1 % output_led4_0_7 $end
$var wire 1 & output_led3_0_6 $end
$var wire 1 ' output_led2_0_5 $end
$var wire 1 ( output_led1_0_4 $end
$var reg 8 ) expected_output [7:0] $end
$var reg 1 * input_input_switch1_1 $end
$var reg 1 + input_input_switch2_2 $end
$var reg 1 , input_input_switch3_3 $end
$var reg 3 - input_value [2:0] $end
$var reg 8 . output_value [7:0] $end
$var integer 32 / pass_count [31:0] $end
$var integer 32 0 test_count [31:0] $end
$scope module dut $end
$var wire 1 1 and_42 $end
$var wire 1 2 and_43 $end
$var wire 1 3 and_44 $end
$var wire 1 4 and_45 $end
$var wire 1 5 and_46 $end
$var wire 1 6 and_47 $end
$var wire 1 7 and_48 $end
$var wire 1 8 and_49 $end
$var wire 1 * input_input_switch1_1 $end
$var wire 1 + input_input_switch2_2 $end
$var wire 1 , input_input_switch3_3 $end
$var wire 1 9 node_12 $end
$var wire 1 : node_13 $end
$var wire 1 ; node_14 $end
$var wire 1 < node_18 $end
$var wire 1 = node_19 $end
$var wire 1 > node_20 $end
$var wire 1 ? node_21 $end
$var wire 1 @ node_22 $end
$var wire 1 A node_23 $end
$var wire 1 B node_24 $end
$var wire 1 C node_25 $end
$var wire 1 D node_26 $end
$var wire 1 E node_27 $end
$var wire 1 F node_28 $end
$var wire 1 G node_29 $end
$var wire 1 H node_30 $end
$var wire 1 I node_31 $end
$var wire 1 J node_32 $end
$var wire 1 K node_33 $end
$var wire 1 L node_34 $end
$var wire 1 M node_35 $end
$var wire 1 N node_36 $end
$var wire 1 O node_37 $end
$var wire 1 P node_38 $end
$var wire 1 Q node_39 $end
$var wire 1 R node_40 $end
$var wire 1 S node_41 $end
$var wire 1 T not_15 $end
$var wire 1 U not_16 $end
$var wire 1 V not_17 $end
$var wire 1 ( output_led1_0_4 $end
$var wire 1 ' output_led2_0_5 $end
$var wire 1 & output_led3_0_6 $end
$var wire 1 % output_led4_0_7 $end
$var wire 1 $ output_led5_0_8 $end
$var wire 1 # output_led6_0_9 $end
$var wire 1 " output_led7_0_10 $end
$var wire 1 ! output_led8_0_11 $end
$upscope $end
$scope task test_decoder $end
$var reg 3 W inputs [2:0] $end
$upscope $end
$upscope $end
$enddefinitions $end
#0
$dumpvars
bx W
1V
1U
1T
0S
0R
0Q
1P
1O
1N
0M
0L
0K
1J
1I
1H
0G
0F
0E
1D
1C
1B
0A
0@
0?
1>
1=
1<
0;
0:
09
08
07
06
05
04
03
02
11
b0 0
b0 /
b10000000 .
bx -
0,
0+
0*
bx )
0(
0'
0&
0%
0$
0#
0"
1!
$end
#50000
b1 )
b0 -
b1 0
b0 W
#60000
0!
01
b100000 .
1#
13
0O
0I
0B
0=
0U
b10 )
b1 -
1R
1L
1F
1@
1:
1*
b10 0
b1 W
#70000
1"
12
b1000000 .
0#
03
0P
0J
0D
0>
0V
1O
1I
1B
1=
1U
b100 )
b10 -
1Q
1K
1E
1?
1;
1+
0R
0L
0F
0@
0:
0*
b11 0
b10 W
#80000
0"
02
b10000 .
1$
14
0O
0I
0B
0=
0U
b1000 )
b11 -
1R
1L
1F
1@
1:
1*
b100 0
b11 W
#90000
1%
15
b1000 .
0N
0H
0C
0<
0T
1P
1J
1D
1>
1V
0$
04
1O
1I
1B
1=
1U
b10000 )
b100 -
1S
1M
1G
1A
19
1,
0Q
0K
0E
0?
0;
0+
0R
0L
0F
0@
0:
0*
b101 0
b100 W
#100000
0%
05
b10 .
1'
17
0O
0I
0B
0=
0U
b100000 )
b101 -
1R
1L
1F
1@
1:
1*
b110 0
b101 W
#110000
1&
16
b100 .
0'
07
0P
0J
0D
0>
0V
1O
1I
1B
1=
1U
b1000000 )
b110 -
1Q
1K
1E
1?
1;
1+
0R
0L
0F
0@
0:
0*
b111 0
b110 W
#120000
0&
06
b1 .
1(
18
0O
0I
0B
0=
0U
b10000000 )
b111 -
1R
1L
1F
1@
1:
1*
b1000 0
b111 W
