test/verilog/dflipflop-masterslave.v
// ====================================================================
// ======= This Verilog code was generated automatically by wiRedPanda =======
// ====================================================================
//
// Module: dflipflop_masterslave
// Generated: Fri Sep 26 19:56:45 2025
// Target FPGA: Generic-Small
// Resource Usage: 10/1000 LUTs, 35/1000 FFs, 4/50 IOs
//
// wiRedPanda - Digital Logic Circuit Simulator
// https://github.com/gibis-unifesp/wiredpanda
// ====================================================================

module dflipflop_masterslave (
    // ========= Input Ports =========
    input wire input_clock1_clk_1,
    input wire input_push_button2_d_2,

    // ========= Output Ports =========
    output wire output_led1_q_0_3,
    output wire output_led2_q_0_4
);

    // ========= Internal Signals =========
// ============== BEGIN IC: DLATCH ==============
// IC inputs: 2, IC outputs: 2
// Nesting depth: 0
    wire ic_dlatch_ic_node_9_0;
    wire ic_dlatch_ic_not_10_0;
    wire ic_dlatch_ic_node_11_0;
    wire ic_dlatch_ic_nand_12_0;
    wire ic_dlatch_ic_nand_13_0;
    wire ic_dlatch_ic_nand_14_0;
    wire ic_dlatch_ic_nand_15_0;
    wire ic_dlatch_ic_node_16_0;
    wire ic_dlatch_ic_node_17_0;
// ============== END IC: DLATCH ==============
// ============== BEGIN IC: DLATCH ==============
// IC inputs: 2, IC outputs: 2
// Nesting depth: 0
    wire ic_dlatch_ic_node_22_0;
    wire ic_dlatch_ic_not_23_0;
    wire ic_dlatch_ic_node_24_0;
    wire ic_dlatch_ic_nand_25_0;
    wire ic_dlatch_ic_nand_26_0;
    wire ic_dlatch_ic_nand_27_0;
    wire ic_dlatch_ic_nand_28_0;
    wire ic_dlatch_ic_node_29_0;
    wire ic_dlatch_ic_node_30_0;
// ============== END IC: DLATCH ==============
    wire not_31;
    wire node_32;
    wire node_33;

    // ========= Logic Assignments =========

    // ========= Internal Sequential Register =========
    reg output_led1_q_0_3_behavioral_reg = 1'b0; // Internal sequential register

    // ========= Behavioral Sequential Logic (replaces gate-level feedback) =========
    // Industry-standard behavioral sequential logic
    always @(posedge input_clock1_clk_1) begin
begin // Synchronous operation
            output_led1_q_0_3_behavioral_reg <= input_push_button2_d_2;
        end
    end

    assign output_led1_q_0_3 = output_led1_q_0_3_behavioral_reg; // Connect behavioral register to output
    assign output_led2_q_0_4 = ~output_led1_q_0_3_behavioral_reg; // Complementary output

    // ========= Output Assignments =========
    assign output_led1_q_0_3 = ic_dlatch_ic_node_29_0; // LED
    assign output_led2_q_0_4 = ic_dlatch_ic_node_30_0; // LED

endmodule // dflipflop_masterslave

// ====================================================================
// Module dflipflop_masterslave generation completed successfully
// Elements processed: 9
// Inputs: 2, Outputs: 2
// Warnings: 1
//   IC DLATCH output 1 is not connected
// ====================================================================

test/verilog/dflipflop_masterslave_tb.v
`timescale 1ns / 1ps

module dflipflop_masterslave_tb;

    // Testbench signals
    reg input_clock1_clk_1;
    reg input_push_button2_d_2;
    wire output_led1_q_0_3;
    wire output_led2_q_0_4;

    // Test control
    integer test_count = 0;
    integer pass_count = 0;
    reg previous_d = 0;
    reg expected_q = 0;

    // Instantiate the Device Under Test (DUT)
    dflipflop_masterslave dut (
        .input_clock1_clk_1(input_clock1_clk_1),
        .input_push_button2_d_2(input_push_button2_d_2),
        .output_led1_q_0_3(output_led1_q_0_3),
        .output_led2_q_0_4(output_led2_q_0_4)
    );

    // Clock generation (10MHz = 100ns period)
    always begin
        #50 input_clock1_clk_1 = ~input_clock1_clk_1;
    end

    // Test procedure for D master-slave flip-flop
    task test_dff;
        input d_value;
        begin
            test_count = test_count + 1;

            // Set D input
            input_push_button2_d_2 = d_value;

            // Wait for setup time
            #10;

            // Clock edge
            @(posedge input_clock1_clk_1);

            // Wait for propagation delay
            #10;

            $display("Test %0d: D=%b => Q=%b, Q̄=%b",
                     test_count, d_value, output_led1_q_0_3, output_led2_q_0_4);

            // Basic validation: Q and Q̄ should be complementary
            if (output_led1_q_0_3 != output_led2_q_0_4) begin
                pass_count = pass_count + 1;
                $display("      PASS: Outputs are complementary");
            end else begin
                $display("      FAIL: Outputs should be complementary");
            end

            // Store expected value for next test
            expected_q = d_value;
        end
    endtask

    // Test D flip-flop hold behavior (D changes while clock is stable)
    task test_hold;
        input d_value;
        begin
            test_count = test_count + 1;

            // Set D input without clock edge
            input_push_button2_d_2 = d_value;

            // Wait without clock edge
            #30;

            $display("Test %0d (Hold): D=%b (no clock) => Q=%b, Q̄=%b",
                     test_count, d_value, output_led1_q_0_3, output_led2_q_0_4);

            // Q should remain the same (hold previous value)
            if (output_led1_q_0_3 != output_led2_q_0_4) begin
                pass_count = pass_count + 1;
                $display("      PASS: Outputs are complementary and held");
            end else begin
                $display("      FAIL: Outputs should be complementary");
            end
        end
    endtask

    // Main test sequence
    initial begin
        $display("=== D MASTER-SLAVE FLIP-FLOP TESTBENCH ===");
        $display("Testing D flip-flop with master-slave architecture");

        // Initialize signals
        input_clock1_clk_1 = 0;
        input_push_button2_d_2 = 0;

        // Wait for initialization
        #100;

        // Test normal D flip-flop operation
        test_dff(0); // D=0, should latch 0
        test_dff(1); // D=1, should latch 1
        test_dff(0); // D=0, should latch 0
        test_dff(1); // D=1, should latch 1

        // Test hold behavior (no clock edge)
        test_hold(0); // Change D but no clock - should hold previous value
        test_hold(1); // Change D but no clock - should hold previous value

        // More clock edge tests
        test_dff(0); // D=0, should latch 0
        test_dff(1); // D=1, should latch 1

        // Test rapid D changes followed by clock
        input_push_button2_d_2 = 0;
        #5;
        input_push_button2_d_2 = 1;
        #5;
        input_push_button2_d_2 = 0;
        #5;
        input_push_button2_d_2 = 1; // Final value before clock
        test_dff(1); // Should latch the final D value

        // Summary
        $display("\n=== TEST SUMMARY ===");
        $display("Total tests: %0d", test_count);
        $display("Passed: %0d", pass_count);
        $display("Failed: %0d", test_count - pass_count);

        if (pass_count == test_count) begin
            $display("*** ALL TESTS PASSED ***");
        end else begin
            $display("*** SOME TESTS FAILED ***");
        end

        $finish;
    end

    // Optional: Generate VCD file for waveform viewing
    initial begin
        $dumpfile("dflipflop_masterslave_tb.vcd");
        $dumpvars(0, dflipflop_masterslave_tb);
    end

endmodule

test/verilog/dflipflop_masterslave_tb.vcd
$date
	Fri Sep 26 21:33:16 2025
$end
$version
	Icarus Verilog
$end
$timescale
	1ps
$end
$scope module dflipflop_masterslave_tb $end
$var wire 1 ! output_led1_q_0_3 $end
$var wire 1 " output_led2_q_0_4 $end
$var reg 1 # expected_q $end
$var reg 1 $ input_clock1_clk_1 $end
$var reg 1 % input_push_button2_d_2 $end
$var reg 1 & previous_d $end
$var integer 32 ' pass_count [31:0] $end
$var integer 32 ( test_count [31:0] $end
$scope module dut $end
$var wire 1 ) ic_dlatch_ic_node_29_0 $end
$var wire 1 * ic_dlatch_ic_node_30_0 $end
$var wire 1 $ input_clock1_clk_1 $end
$var wire 1 % input_push_button2_d_2 $end
$var wire 1 ! output_led1_q_0_3 $end
$var wire 1 " output_led2_q_0_4 $end
$var reg 1 + output_led1_q_0_3_behavioral_reg $end
$upscope $end
$scope task test_dff $end
$var reg 1 , d_value $end
$upscope $end
$scope task test_hold $end
$var reg 1 - d_value $end
$upscope $end
$upscope $end
$enddefinitions $end
#0
$dumpvars
x-
x,
0+
z*
z)
b0 (
b0 '
0&
0%
0$
0#
1"
0!
$end
#50000
1$
#100000
0$
b1 (
0,
#150000
1$
#160000
1%
b10 (
1,
b1 '
#200000
0$
#250000
0"
1!
1+
1$
#260000
0%
b11 (
0,
1#
b10 '
#300000
0$
#350000
1"
0!
0+
1$
#360000
1%
b100 (
1,
0#
b11 '
#400000
0$
#450000
0"
1!
1+
1$
#460000
0%
b101 (
0-
1#
b100 '
#490000
1%
b110 (
1-
b101 '
#500000
0$
#520000
0%
b111 (
0,
b110 '
#550000
1"
0!
0+
1$
#560000
1%
b1000 (
1,
0#
b111 '
#600000
0$
#650000
0"
1!
1+
1$
#660000
0%
1#
b1000 '
#665000
1%
#670000
0%
#675000
b1001 (
1%
#700000
0$
#750000
1$
#760000
b1001 '
