test/verilog/jkflipflop.v
// ====================================================================
// ======= This Verilog code was generated automatically by wiRedPanda =======
// ====================================================================
//
// Module: jkflipflop
// Generated: Fri Sep 26 19:56:52 2025
// Target FPGA: Generic-Small
// Resource Usage: 24/1000 LUTs, 35/1000 FFs, 7/50 IOs
//
// wiRedPanda - Digital Logic Circuit Simulator
// https://github.com/gibis-unifesp/wiredpanda
// ====================================================================

module jkflipflop (
    // ========= Input Ports =========
    input wire input_clock1_c_1,
    input wire input_input_switch2__preset_2,
    input wire input_input_switch3__clear_3,
    input wire input_input_switch4_j_4,
    input wire input_input_switch5_k_5,

    // ========= Output Ports =========
    output wire output_led1_q_0_6,
    output wire output_led2_q_0_7
);

    // ========= Internal Signals =========
// ============== BEGIN IC: DFLIPFLOP ==============
// IC inputs: 4, IC outputs: 2
// Nesting depth: 0
    wire ic_dflipflop_ic_node_16_0;
    wire ic_dflipflop_ic_not_17_0;
    wire ic_dflipflop_ic_not_18_0;
    wire ic_dflipflop_ic_node_19_0;
    wire ic_dflipflop_ic_node_20_0;
    wire ic_dflipflop_ic_node_21_0;
    wire ic_dflipflop_ic_node_22_0;
    wire ic_dflipflop_ic_nand_23_0;
    wire ic_dflipflop_ic_not_24_0;
    wire ic_dflipflop_ic_node_25_0;
    wire ic_dflipflop_ic_node_26_0;
    wire ic_dflipflop_ic_node_27_0;
    wire ic_dflipflop_ic_node_28_0;
    wire ic_dflipflop_ic_nand_29_0;
    wire ic_dflipflop_ic_nand_30_0;
    wire ic_dflipflop_ic_node_31_0;
    wire ic_dflipflop_ic_nand_32_0;
    wire ic_dflipflop_ic_nand_33_0;
    wire ic_dflipflop_ic_node_34_0;
    wire ic_dflipflop_ic_nand_35_0;
    wire ic_dflipflop_ic_nand_36_0;
    wire ic_dflipflop_ic_node_37_0;
    wire ic_dflipflop_ic_nand_38_0;
    wire ic_dflipflop_ic_node_39_0;
    wire ic_dflipflop_ic_node_40_0;
// ============== END IC: DFLIPFLOP ==============
    wire node_41;
    wire node_42;
    wire node_43;
    wire node_44;
    wire node_45;
    wire node_46;
    wire node_47;
    wire not_48;
    wire node_49;
    wire and_50;
    wire and_51;
    wire or_52;

    // ========= Logic Assignments =========

    // ========= Internal Sequential Register =========
    reg output_led1_q_0_6_behavioral_reg = 1'b0; // Internal sequential register

    // ========= Behavioral Sequential Logic (replaces gate-level feedback) =========
    // Industry-standard behavioral sequential logic
    always @(posedge input_clock1_c_1 or negedge input_input_switch2__preset_2) begin
        if (!input_input_switch2__preset_2) begin
            output_led1_q_0_6_behavioral_reg <= 1'b1; // Asynchronous preset
        end else begin // Synchronous operation
            output_led1_q_0_6_behavioral_reg <= input_input_switch2__preset_2;
        end
    end

    assign output_led1_q_0_6 = output_led1_q_0_6_behavioral_reg; // Connect behavioral register to output
    assign output_led2_q_0_7 = ~output_led1_q_0_6_behavioral_reg; // Complementary output

    // ========= Output Assignments =========
    assign output_led1_q_0_6 = ic_dflipflop_ic_node_39_0; // LED
    assign output_led2_q_0_7 = ic_dflipflop_ic_node_40_0; // LED

endmodule // jkflipflop

// ====================================================================
// Module jkflipflop generation completed successfully
// Elements processed: 20
// Inputs: 5, Outputs: 2
// ====================================================================

test/verilog/jkflipflop_tb.v
`timescale 1ns / 1ps

module jkflipflop_tb;

    // Testbench signals
    reg input_clock1_c_1;
    reg input_input_switch2__preset_2;
    reg input_input_switch3__clear_3;
    reg input_input_switch4_j_4;
    reg input_input_switch5_k_5;
    wire output_led1_q_0_6;
    wire output_led2_q_0_7;

    // Test control
    integer test_count = 0;
    integer pass_count = 0;
    reg previous_q = 0;

    // Instantiate the Device Under Test (DUT)
    jkflipflop dut (
        .input_clock1_c_1(input_clock1_c_1),
        .input_input_switch2__preset_2(input_input_switch2__preset_2),
        .input_input_switch3__clear_3(input_input_switch3__clear_3),
        .input_input_switch4_j_4(input_input_switch4_j_4),
        .input_input_switch5_k_5(input_input_switch5_k_5),
        .output_led1_q_0_6(output_led1_q_0_6),
        .output_led2_q_0_7(output_led2_q_0_7)
    );

    // Clock generation (5MHz = 200ns period)
    always begin
        #100 input_clock1_c_1 = ~input_clock1_c_1;
    end

    // Test procedure for JK flip-flop
    task test_jkff;
        input j_value;
        input k_value;
        input preset;
        input clear;
        begin
            test_count = test_count + 1;

            // Set control signals
            input_input_switch2__preset_2 = preset;
            input_input_switch3__clear_3 = clear;
            input_input_switch4_j_4 = j_value;
            input_input_switch5_k_5 = k_value;

            // Wait for setup time
            #10;

            // Store previous Q state
            previous_q = output_led1_q_0_6;

            // Clock edge
            @(posedge input_clock1_c_1);

            // Wait for propagation delay
            #20;

            $display("Test %0d: J=%b, K=%b, Preset=%b, Clear=%b => Q=%b, Q̄=%b (prev_Q=%b)",
                     test_count, j_value, k_value, preset, clear, output_led1_q_0_6, output_led2_q_0_7, previous_q);

            // Basic validation: Q and Q̄ should be complementary in normal operation
            if (preset == 1 && clear == 1) begin
                if (output_led1_q_0_6 != output_led2_q_0_7) begin
                    // Check JK flip-flop behavior
                    case ({j_value, k_value})
                        2'b00: begin // Hold
                            if (output_led1_q_0_6 == previous_q) begin
                                $display("      PASS: J=0,K=0 held output correctly");
                                pass_count = pass_count + 1;
                            end else begin
                                $display("      FAIL: J=0,K=0 should hold output");
                            end
                        end
                        2'b01: begin // Reset
                            if (output_led1_q_0_6 == 0) begin
                                $display("      PASS: J=0,K=1 reset output correctly");
                                pass_count = pass_count + 1;
                            end else begin
                                $display("      FAIL: J=0,K=1 should reset output to 0");
                            end
                        end
                        2'b10: begin // Set
                            if (output_led1_q_0_6 == 1) begin
                                $display("      PASS: J=1,K=0 set output correctly");
                                pass_count = pass_count + 1;
                            end else begin
                                $display("      FAIL: J=1,K=0 should set output to 1");
                            end
                        end
                        2'b11: begin // Toggle
                            if (output_led1_q_0_6 != previous_q) begin
                                $display("      PASS: J=1,K=1 toggled output correctly");
                                pass_count = pass_count + 1;
                            end else begin
                                $display("      FAIL: J=1,K=1 should toggle output");
                            end
                        end
                    endcase
                end else begin
                    $display("      FAIL: Outputs should be complementary");
                end
            end else begin
                // For preset/clear conditions, just report the state
                if (preset == 0) begin
                    $display("      INFO: Preset active");
                end
                if (clear == 0) begin
                    $display("      INFO: Clear active");
                end
                pass_count = pass_count + 1; // Count as pass for control conditions
            end
        end
    endtask

    // Main test sequence
    initial begin
        $display("=== JK FLIP-FLOP TESTBENCH ===");
        $display("Testing JK flip-flop with preset and clear");

        // Initialize signals
        input_clock1_c_1 = 0;
        input_input_switch4_j_4 = 0;
        input_input_switch5_k_5 = 0;
        input_input_switch2__preset_2 = 1; // Inactive (assuming active low)
        input_input_switch3__clear_3 = 1;  // Inactive (assuming active low)

        // Wait for initialization
        #150;

        // Test all JK flip-flop combinations
        $display("\nTesting JK flip-flop truth table:");
        test_jkff(0, 0, 1, 1); // Hold
        test_jkff(0, 1, 1, 1); // Reset
        test_jkff(1, 0, 1, 1); // Set
        test_jkff(1, 1, 1, 1); // Toggle

        // Test multiple toggles
        $display("\nTesting multiple toggles:");
        test_jkff(1, 1, 1, 1); // Toggle
        test_jkff(1, 1, 1, 1); // Toggle
        test_jkff(1, 1, 1, 1); // Toggle

        // Test hold after various states
        $display("\nTesting hold behavior:");
        test_jkff(1, 0, 1, 1); // Set
        test_jkff(0, 0, 1, 1); // Hold
        test_jkff(0, 1, 1, 1); // Reset
        test_jkff(0, 0, 1, 1); // Hold

        // Test preset functionality (if active low)
        $display("\nTesting preset functionality:");
        test_jkff(0, 0, 0, 1); // Preset active
        test_jkff(1, 1, 1, 1); // Return to normal, toggle

        // Test clear functionality (if active low)
        $display("\nTesting clear functionality:");
        test_jkff(1, 0, 1, 0); // Clear active
        test_jkff(1, 1, 1, 1); // Return to normal, toggle

        // Summary
        $display("\n=== TEST SUMMARY ===");
        $display("Total tests: %0d", test_count);
        $display("Passed: %0d", pass_count);
        $display("Failed: %0d", test_count - pass_count);

        if (pass_count == test_count) begin
            $display("*** ALL TESTS PASSED ***");
        end else begin
            $display("*** SOME TESTS FAILED ***");
        end

        $finish;
    end

    // Optional: Generate VCD file for waveform viewing
    initial begin
        $dumpfile("jkflipflop_tb.vcd");
        $dumpvars(0, jkflipflop_tb);
    end

endmodule

test/verilog/jkflipflop_tb.vcd
$date
	Fri Sep 26 21:01:40 2025
$end
$version
	Icarus Verilog
$end
$timescale
	1ps
$end
$scope module jkflipflop_tb $end
$var wire 1 ! output_led1_q_0_6 $end
$var wire 1 " output_led2_q_0_7 $end
$var reg 1 # input_clock1_c_1 $end
$var reg 1 $ input_input_switch2__preset_2 $end
$var reg 1 % input_input_switch3__clear_3 $end
$var reg 1 & input_input_switch4_j_4 $end
$var reg 1 ' input_input_switch5_k_5 $end
$var reg 1 ( previous_q $end
$var integer 32 ) pass_count [31:0] $end
$var integer 32 * test_count [31:0] $end
$scope module dut $end
$var wire 1 + ic_dflipflop_ic_node_39_0 $end
$var wire 1 , ic_dflipflop_ic_node_40_0 $end
$var wire 1 # input_clock1_c_1 $end
$var wire 1 $ input_input_switch2__preset_2 $end
$var wire 1 % input_input_switch3__clear_3 $end
$var wire 1 & input_input_switch4_j_4 $end
$var wire 1 ' input_input_switch5_k_5 $end
$var wire 1 ! output_led1_q_0_6 $end
$var wire 1 " output_led2_q_0_7 $end
$var reg 1 - output_led1_q_0_6_behavioral_reg $end
$upscope $end
$scope task test_jkff $end
$var reg 1 . clear $end
$var reg 1 / j_value $end
$var reg 1 0 k_value $end
$var reg 1 1 preset $end
$upscope $end
$upscope $end
$enddefinitions $end
#0
$dumpvars
x1
x0
x/
x.
0-
z,
z+
b0 *
b0 )
0(
0'
0&
1%
1$
0#
1"
0!
$end
#100000
0"
1!
1-
1#
#150000
b1 *
1.
11
00
0/
#160000
1(
#200000
0#
#300000
1#
#320000
1'
b10 *
10
b1 )
#400000
0#
#500000
1#
#520000
0'
1&
b11 *
00
1/
#600000
0#
#700000
1#
#720000
1'
b100 *
10
b10 )
#800000
0#
#900000
1#
#920000
b101 *
#1000000
0#
#1100000
1#
#1120000
b110 *
#1200000
0#
#1300000
1#
#1320000
b111 *
#1400000
0#
#1500000
1#
#1520000
0'
b1000 *
00
#1600000
0#
#1700000
1#
#1720000
0&
b1001 *
0/
b11 )
#1800000
0#
#1900000
1#
#1920000
1'
b1010 *
10
b100 )
#2000000
0#
#2100000
1#
#2120000
0'
b1011 *
00
#2200000
0#
#2300000
1#
#2320000
0$
b1100 *
01
b101 )
#2400000
0#
#2500000
1#
#2520000
1'
1&
1$
b1101 *
11
10
1/
b110 )
#2600000
0#
#2700000
1#
#2720000
0'
0%
b1110 *
0.
00
#2800000
0#
#2900000
1#
#2920000
1'
1%
b1111 *
1.
10
b111 )
